{
  "id": "579eb092",
  "name": "Flagstaff Point Lighthouse (Wollongong Head)",
  "name_ko": "플래그스태프 포인트 등대 (울릉공 헤드)",
  "category": "attraction",
  "source_file": "2026-03-13.json",
  "address_raw": "Flagstaff Point Lighthouse, lot 2500/LOT 2 Endeavour Dr, Wollongong NSW 2500 오스트레일리아",
  "location": {
    "coordinates": {
      "lng": 150.90973,
      "lat": -34.4218855
    },
    "address": "Endeavour Dr, Wollongong NSW 2500, Australia",
    "region": "울릉공/키아마"
  },
  "collected_data": {
    "rating": 4.5,
    "total_reviews": 700,
    "price_level": null,
    "opening_hours": "상시 개방 (외부 부지). 등대 내부 비공개.",
    "review_summary": {
      "same_month_last_year": {
        "period": "2025-05",
        "count": 0,
        "positive": [
          "태즈먼해 장관의 파노라마 뷰",
          "1936년 건설된 NSW 최초 자동 등대의 역사적 가치",
          "호주 동해안 유일하게 등대 2개 있는 울릉공의 상징"
        ],
        "negative": [
          "등대 내부 비공개로 외관만 관람",
          "전망 외 체류 시간 짧음"
        ],
        "seasonal_notes": "5월 가을 — 맑은 날 일라와라 해안 조망 선명. 고래 이동 관찰 가능."
      },
      "recent_6_months": {
        "period": "2025-09 ~ 2026-03",
        "count": 0,
        "positive": [
          "주변 공원에서 피크닉 가능",
          "구 배터리 방어시설을 아이들이 탐험",
          "북쪽 일라와라 해안선과 남쪽 포트 켐블라 전망"
        ],
        "negative": [
          "독립 방문보다 울릉공 해안 워크의 일부로 방문 권장"
        ],
        "status_notes": "정상 운영 중"
      },
      "tips": [
        "무료 입장, 충분한 주차 공간",
        "울릉공 해안 워크(Coastal Walk)의 일부로 연계",
        "인근 카페에서 커피 가능",
        "Pilots' Cottage Museum (구 등대지기 주택) 방문 가능"
      ]
    },
    "collected_at": "2026-03-13T00:00:00Z",
    "logistics": {
      "parking": "충분한 무료 주차. Endeavour Dr 부근.",
      "road_condition": "포장 양호. 울릉공 시내에서 차로 5분.",
      "nearby_attractions": [
        {
          "name": "Sea Cliff Bridge (96da6ea2)",
          "distance_km": 20,
          "drive_min": 25
        },
        {
          "name": "Bushrangers Bay (5254b0bc)",
          "distance_km": 20,
          "drive_min": 25
        },
        {
          "name": "Bombo Headland (a43e5009)",
          "distance_km": 35,
          "drive_min": 35
        }
      ],
      "peak_times": "주말 오후. 평일은 한적.",
      "public_transport": "울릉공역에서 버스 또는 도보 20분"
    },
    "experience": {
      "photo_spots": [
        "등대 + 태즈먼해 배경",
        "Flagstaff Hill에서 북쪽 해안선 파노라마",
        "구 배터리 방어시설과 등대"
      ],
      "golden_hour": "일출 시 동쪽 바다에서 등대를 비추는 황금빛. 일몰 시 에스카프먼트 뒤로 석양.",
      "seasonal_beauty": "5월 가을 — 선명한 해안 조망과 고래 관찰 가능",
      "hidden_gems": [
        "Pilots' Cottage Museum — 등대지기 역사 전시"
      ],
      "sensory_notes": "절벽 위 바닷바람, 시원한 바다 공기, 탁 트인 수평선의 개방감"
    },
    "risk_check": {
      "negative_review_patterns": [
        "체류 시간 짧음",
        "등대 내부 비공개"
      ],
      "may_operation": "정상 운영.",
      "safety_issues": "절벽 가장자리 주의. 공원 내 안전한 산책로.",
      "weather_impact": "우천 시 전망 제한. 강풍 가능. 접근 자체는 영향 없음.",
      "quality_trend": "안정적 유지. 공원 관리 양호."
    }
  },
  "metadata": {
    "estimated_visit_duration_min": 30,
    "cost_aud": 0,
    "best_time": "오전~오후 (맑은 날)",
    "weather_dependent": true,
    "reservation_required": false
  },
  "google_maps_url": "https://www.google.com/maps/search/?api=1&query=Flagstaff+Point+Lighthouse,+Endeavour+Dr,+Wollongong+NSW+2500,+Australia"
}